remarkable_mouse/__init__.py
remarkable_mouse/codes.py
remarkable_mouse/common.py
remarkable_mouse/evdev.py
remarkable_mouse/generate_codes.py
remarkable_mouse/pynput.py
remarkable_mouse/remarkable_mouse.py
remarkable_mouse/version.py
remarkable_mouse-7.1.1.dist-info/LICENSE
remarkable_mouse-7.1.1.dist-info/METADATA
remarkable_mouse-7.1.1.dist-info/WHEEL
remarkable_mouse-7.1.1.dist-info/entry_points.txt
remarkable_mouse-7.1.1.dist-info/top_level.txt
remarkable_mouse-7.1.1.dist-info/RECORD
