Metadata-Version: 2.1
Name: remarkable-mouse
Version: 7.1.1
Summary: use reMarkable as a graphics tablet
Home-page: https://github.com/evidlo/remarkable_mouse
Author: Evan Widloski
Author-email: evan@evanw.org
License: GPLv3
Keywords: remarkable tablet evdev
Platform: UNKNOWN
Classifier: Programming Language :: Python :: 3
License-File: LICENSE
Requires-Dist: libevdev
Requires-Dist: paramiko
Requires-Dist: pynput
Requires-Dist: screeninfo
